moleval/__init__.py
moleval/utils.py
moleval/metrics/__init__.py
moleval/metrics/chemistry_filters.py
moleval/metrics/ifg.py
moleval/metrics/mcf.csv
moleval/metrics/metrics.py
moleval/metrics/metrics_utils.py
moleval/metrics/score_metrics.py
moleval/metrics/test_score_metrics.py
moleval/metrics/wehi_pains.csv
moleval/metrics/NP_Score/README
moleval/metrics/NP_Score/__init__.py
moleval/metrics/NP_Score/npscorer.py
moleval/metrics/NP_Score/publicnp.model.gz
moleval/metrics/SA_Score/README
moleval/metrics/SA_Score/UnitTestSAScore.py
moleval/metrics/SA_Score/__init__.py
moleval/metrics/SA_Score/fpscores.pkl.gz
moleval/metrics/SA_Score/sascorer.py
moleval/metrics/SA_Score/data/zim.100.txt
moleval/metrics/fcd_torch/ChemNet_v0.13_pretrained.pt
moleval/metrics/fcd_torch/LICENSE
moleval/metrics/fcd_torch/README.md
moleval/metrics/fcd_torch/__init__.py
moleval/metrics/fcd_torch/fcd.py
moleval/metrics/fcd_torch/keras2pytorch.py
moleval/metrics/fcd_torch/test.py
moleval/metrics/fcd_torch/torch_layers.py
moleval/metrics/fcd_torch/utils.py
moleval/metrics/posecheck/LICENSE
moleval/metrics/posecheck/__init__.py
moleval/metrics/posecheck/posecheck.py
moleval/metrics/posecheck/utils/__init__.py
moleval/metrics/posecheck/utils/chem.py
moleval/metrics/posecheck/utils/clashes.py
moleval/metrics/posecheck/utils/constants.py
moleval/metrics/posecheck/utils/docking.py
moleval/metrics/posecheck/utils/docking_utils.py
moleval/metrics/posecheck/utils/interactions.py
moleval/metrics/posecheck/utils/loading.py
moleval/metrics/posecheck/utils/strain.py
moleval/metrics/quality_filters/README.md
moleval/metrics/quality_filters/__init__.py
moleval/metrics/quality_filters/alert_collection.csv
moleval/metrics/quality_filters/guacamol_rules.json
moleval/metrics/quality_filters/rd_filters.py
moleval/molvs/CHANGELOG.md
moleval/molvs/CONTRIBUTING.rst
moleval/molvs/LICENSE
moleval/molvs/README.rst
moleval/molvs/__init__.py
moleval/molvs/charge.py
moleval/molvs/cli.py
moleval/molvs/errors.py
molscore-1.9.5.dist-info/licenses/LICENSE
molscore-1.9.5.dist-info/METADATA
molscore-1.9.5.dist-info/WHEEL
molscore-1.9.5.dist-info/top_level.txt
molscore-1.9.5.dist-info/RECORD
