Metadata-Version: 2.4
Name: MolScore
Version: 1.9.5
Summary: A scoring, benchmarking and evaluation framework for goal directed generative models
Author-email: Morgan Thomas <morganthomas263@gmail.com>
License-Expression: MIT
Project-URL: Homepage, https://github.com/MorganCThomas/MolScore
Project-URL: Issues, https://github.com/MorganCThomas/MolScore/issues
Classifier: Programming Language :: Python :: 3
Classifier: Operating System :: OS Independent
Requires-Python: >=3.6
License-File: LICENSE
Requires-Dist: numpy
Requires-Dist: pandas
Requires-Dist: matplotlib
Requires-Dist: seaborn
Requires-Dist: tqdm
Requires-Dist: rdkit>=2019.03.2
Requires-Dist: dask
Requires-Dist: dask-jobqueue
Requires-Dist: torch
Requires-Dist: levenshtein
Requires-Dist: streamlit-plotly-events==0.0.6
Requires-Dist: streamlit>=1.11.0
Requires-Dist: molbloom
Requires-Dist: func_timeout
Requires-Dist: flask
Dynamic: license-file
Dynamic: requires-dist
